{
  "required": true,
  "minVersion": "0.8",
  "package": "me.senseiwells.replay.mixin",
  "compatibilityLevel": "JAVA_17",
  "plugin": "me.senseiwells.replay.util.ReplayMixinConfig",
  "mixins": [
    "CommandsMixin",
    "MinecraftServerMixin",
    "ServerCommonPacketListenerImplMixin",
    "ServerConfigurationPacketListenerImplMixin",
    "ServerLevelMixin",
    "ServerLoginPacketListenerImplMixin",
    "ServerPlayerMixin",
    "compat.carpet.NetHandlerPlayServerFakeMixin",
    "rejoin.ChunkMapAccessor",
    "rejoin.ChunkMapMixin",
    "rejoin.ConnectionAccessor",
    "rejoin.ServerConfigurationPacketListenerImplAccessor",
    "rejoin.ServerPlayerMixin",
    "rejoin.TrackedEntityAccessor",
    "rejoin.TrackedEntityMixin",
    "studio.ZipReplayFileAccessor"
  ],
  "injectors": {
    "defaultRequire": 1
  }
}